st_cookie_manager/__init__.py
st_cookie_manager/cookie_manager.py
st_cookie_manager/encrypted_cookie_manager.py
st_cookie_manager/package-lock.json
st_cookie_manager/package.json
st_cookie_manager/public/index.html
st_cookie_manager/src/index.ts
st_cookie_manager/src/react-app-env.d.ts
st_cookie_manager/tsconfig.json
st_cookie_manager-0.1.0.dist-info/METADATA
st_cookie_manager-0.1.0.dist-info/WHEEL
st_cookie_manager-0.1.0.dist-info/RECORD
