Metadata-Version: 2.1
Name: st-cookie-manager
Version: 0.1.0
Summary: Access and save cookies from Streamlit
License: Apache-2.0
Author: xiaoqinglin
Author-email: xiaoqinglin2018@gmail.com
Requires-Python: >=3.12,<4.0
Classifier: License :: OSI Approved :: Apache Software License
Classifier: Programming Language :: Python :: 3
Classifier: Programming Language :: Python :: 3.12
Requires-Dist: cryptography
Requires-Dist: streamlit (>=1.37.1,<2.0.0)
